django_pgtree/__init__.py
django_pgtree/fields.py
django_pgtree/migrations/0001_initial.py
django_pgtree/migrations/__init__.py
django_pgtree/models.py
django_pgtree/tests.py
django_pgtree-0.1.4.dist-info/WHEEL
django_pgtree-0.1.4.dist-info/METADATA
django_pgtree-0.1.4.dist-info/RECORD
