Metadata-Version: 2.1
Name: django-pgtree
Version: 0.1.4
Summary: Heirachial data for Django with Postgres.
Home-page: UNKNOWN
License: ISC
Author: Adam Brenecki
Requires-Python: >=3.4
Classifier: License :: OSI Approved
Classifier: Programming Language :: Python :: 3
Classifier: Programming Language :: Python :: 3.4
Classifier: Programming Language :: Python :: 3.5
Classifier: Programming Language :: Python :: 3.6
Classifier: Programming Language :: Python :: 3.7
